retrylib/__init__.py
retrylib/decorators.py
retrylib/defaults.py
retrylib/network.py
retrylib-1.2.5.dist-info/AUTHORS
retrylib-1.2.5.dist-info/LICENSE
retrylib-1.2.5.dist-info/METADATA
retrylib-1.2.5.dist-info/WHEEL
retrylib-1.2.5.dist-info/pbr.json
retrylib-1.2.5.dist-info/top_level.txt
retrylib-1.2.5.dist-info/RECORD
