Metadata-Version: 2.1
Name: retrylib
Version: 1.2.5
Summary: Smart retry library
Home-page: https://github.com/sbunatyan/retrylib
Author: Sergey Bunatyan
Author-email: sergey.bunatian@gmail.com
License: Apache License 2.0
Download-URL: https://github.com/sbunatyan/retrylib/tree/1.2.5
Keywords: retry,retries
Platform: UNKNOWN
Classifier: License :: OSI Approved :: Apache Software License
Classifier: Operating System :: POSIX :: Linux
Classifier: Programming Language :: Python
Classifier: Programming Language :: Python :: 2
Classifier: Programming Language :: Python :: 2.7
Classifier: Programming Language :: Python :: 3.5
Requires-Dist: requests
Requires-Dist: six
